nyxboard/__init__.py
nyxboard/apps.py
nyxboard/devdata.py
nyxboard/forms.py
nyxboard/models.py
nyxboard/urls.py
nyxboard/views.py
nyxboard/management/__init__.py
nyxboard/management/commands/__init__.py
nyxboard/management/commands/create_devdata.py
nyxboard/migrations/0001_initial.py
nyxboard/migrations/0002_healthcheck_next_check_time.py
nyxboard/migrations/0003_healthcheck_processing_started_at.py
nyxboard/migrations/0004_healthcheck_status.py
nyxboard/migrations/0005_add_name.py
nyxboard/migrations/0006_add_disabled_flag.py
nyxboard/migrations/0007_add_disabled_field.py
nyxboard/migrations/0008_alter_healthcheck_check_type.py
nyxboard/migrations/__init__.py
nyxboard/static/css/styles.css
nyxboard/static/css/theme.css
nyxboard/static/js/dashboard.js
nyxboard/static/js/components/check-timer.js
nyxboard/static/js/components/health-check.js
nyxboard/static/js/components/progress-ring.js
nyxboard/static/js/components/service-card.js
nyxboard/static/js/tests/health-check.test.js
nyxboard/static/js/tests/progress-ring.test.js
nyxboard/static/js/tests/setup.js
nyxboard/templates/base.html
nyxboard/templates/nyxboard/dashboard.html
nyxboard/templates/nyxboard/form_base.html
nyxboard/templates/nyxboard/healthcheck_confirm_delete.html
nyxboard/templates/nyxboard/healthcheck_detail.html
nyxboard/templates/nyxboard/healthcheck_form.html
nyxboard/templates/nyxboard/healthcheck_list.html
nyxboard/templates/nyxboard/service_confirm_delete.html
nyxboard/templates/nyxboard/service_detail.html
nyxboard/templates/nyxboard/service_form.html
nyxboard/templates/nyxboard/service_list.html
nyxboard/templates/nyxboard/partials/healthcheck-card.html
nyxboard/templates/nyxboard/partials/healthcheck.html
nyxmon/__init__.py
nyxmon/bootstrap.py
nyxmon/py.typed
nyxmon/adapters/collector.py
nyxmon/adapters/notification.py
nyxmon/adapters/repositories/__init__.py
nyxmon/adapters/repositories/in_memory.py
nyxmon/adapters/repositories/interface.py
nyxmon/adapters/repositories/sqlite_repo.py
nyxmon-0.1.4.dist-info/METADATA
nyxmon-0.1.4.dist-info/WHEEL
nyxmon-0.1.4.dist-info/entry_points.txt
nyxmon-0.1.4.dist-info/licenses/LICENSE
nyxmon-0.1.4.dist-info/RECORD
