Metadata-Version: 2.4
Name: nyxmon
Version: 0.1.4
Summary: Minimal monitoring package
Author-email: Jochen Wersdörfer <jochen-nyxmon@wersdoerfer.de>
License-File: LICENSE
Requires-Python: >=3.12
Requires-Dist: aiosqlite>=0.21.0
Requires-Dist: django
Requires-Dist: django-environ
Requires-Dist: django-htmx
Requires-Dist: granian>=0.8.0
Requires-Dist: httpx>=0.28.1
Requires-Dist: psutil>=5.9.5
Requires-Dist: uvloop>=0.21.0
Requires-Dist: whitenoise
